[
  {
    "name": "minScore",
    "expected": 0.85,
    "actual": 0.77,
    "values": [
      0.75,
      0.77,
      0.59
    ],
    "operator": ">=",
    "passed": false,
    "auditProperty": "performance",
    "auditId": "categories",
    "level": "error",
    "url": "http://localhost:4173/"
  },
  {
    "name": "minScore",
    "expected": 0.9,
    "actual": 0.83,
    "values": [
      0.83,
      0.83,
      0.83
    ],
    "operator": ">=",
    "passed": false,
    "auditProperty": "seo",
    "auditId": "categories",
    "level": "error",
    "url": "http://localhost:4173/"
  },
  {
    "name": "auditRan",
    "expected": 1,
    "actual": 0,
    "values": [
      0,
      0,
      0
    ],
    "operator": ">=",
    "passed": false,
    "auditProperty": "pwa",
    "auditId": "categories",
    "level": "error",
    "url": "http://localhost:4173/"
  },
  {
    "name": "maxNumericValue",
    "expected": 2500,
    "actual": 3954.4606249999997,
    "values": [
      4084.28575,
      3954.4606249999997,
      15710.749649999996
    ],
    "operator": "<=",
    "passed": false,
    "auditId": "largest-contentful-paint",
    "level": "error",
    "url": "http://localhost:4173/",
    "auditTitle": "Largest Contentful Paint",
    "auditDocumentationLink": "https://developer.chrome.com/docs/lighthouse/performance/lighthouse-largest-contentful-paint/"
  },
  {
    "name": "maxNumericValue",
    "expected": 1800,
    "actual": 3051.5632000000005,
    "values": [
      3095.794,
      3054.4440000000004,
      3051.5632000000005
    ],
    "operator": "<=",
    "passed": false,
    "auditId": "first-contentful-paint",
    "level": "error",
    "url": "http://localhost:4173/",
    "auditTitle": "First Contentful Paint",
    "auditDocumentationLink": "https://developer.chrome.com/docs/lighthouse/performance/first-contentful-paint/"
  },
  {
    "name": "maxNumericValue",
    "expected": 1048576,
    "actual": 3709371,
    "values": [
      3709371,
      3709371,
      3709371
    ],
    "operator": "<=",
    "passed": false,
    "auditId": "total-byte-weight",
    "level": "error",
    "url": "http://localhost:4173/",
    "auditTitle": "Avoid enormous network payloads",
    "auditDocumentationLink": "https://developer.chrome.com/docs/lighthouse/performance/total-byte-weight/"
  },
  {
    "name": "minScore",
    "expected": 0.9,
    "actual": 0.5,
    "values": [
      0.5,
      0.5,
      0.5
    ],
    "operator": ">=",
    "passed": false,
    "auditId": "modern-image-formats",
    "level": "error",
    "url": "http://localhost:4173/",
    "auditTitle": "Serve images in next-gen formats",
    "auditDocumentationLink": "https://developer.chrome.com/docs/lighthouse/performance/uses-webp-images/"
  },
  {
    "name": "auditRan",
    "expected": 1,
    "actual": 0,
    "values": [
      0,
      0,
      0
    ],
    "operator": ">=",
    "passed": false,
    "message": "\"uses-webp-images\" is not a known audit.",
    "auditId": "uses-webp-images",
    "level": "error",
    "url": "http://localhost:4173/"
  },
  {
    "name": "minScore",
    "expected": 0.9,
    "actual": 0,
    "values": [
      0,
      0,
      0
    ],
    "operator": ">=",
    "passed": false,
    "auditId": "render-blocking-resources",
    "level": "warn",
    "url": "http://localhost:4173/",
    "auditTitle": "Eliminate render-blocking resources",
    "auditDocumentationLink": "https://developer.chrome.com/docs/lighthouse/performance/render-blocking-resources/"
  },
  {
    "name": "minScore",
    "expected": 0.9,
    "actual": 0.5,
    "values": [
      0.5,
      0.5,
      0
    ],
    "operator": ">=",
    "passed": false,
    "auditId": "uses-responsive-images",
    "level": "error",
    "url": "http://localhost:4173/",
    "auditTitle": "Properly size images",
    "auditDocumentationLink": "https://developer.chrome.com/docs/lighthouse/performance/uses-responsive-images/"
  },
  {
    "name": "auditRan",
    "expected": 1,
    "actual": 0,
    "values": [
      0,
      0,
      0
    ],
    "operator": ">=",
    "passed": false,
    "message": "\"properly-size-images\" is not a known audit.",
    "auditId": "properly-size-images",
    "level": "error",
    "url": "http://localhost:4173/"
  }
]